LICENSE.txt
MANIFEST.in
README.md
androidenv.py
setup.cfg
setup.py
androidenv.egg-info/PKG-INFO
androidenv.egg-info/SOURCES.txt
androidenv.egg-info/dependency_links.txt
androidenv.egg-info/top_level.txt