Metadata-Version: 2.1
Name: androidenv
Version: 1.0
Summary: Build native packages for Android
Home-page: https://github.com/mansourmoufid/python-androidenv
Author: Mansour Moufid
Author-email: mansourmoufid@gmail.com
License: ISC
Keywords: android
Platform: UNKNOWN
Classifier: Development Status :: 4 - Beta
Classifier: Environment :: Console
Classifier: Intended Audience :: Developers
Classifier: License :: OSI Approved :: ISC License (ISCL)
Classifier: Operating System :: Android
Classifier: Operating System :: OS Independent
Classifier: Programming Language :: Python
Classifier: Topic :: Software Development :: Build Tools
